spcalc/__init__.py
spcalc/add.py
spcalc/calculator.py
spcalc/divide.py
spcalc/main.py
spcalc/multiply.py
spcalc/operation.py
spcalc/subtract.py
tests/__init__.py
tests/test_calculator.py
spcalc-2.0.0.dist-info/LICENSE
spcalc-2.0.0.dist-info/METADATA
spcalc-2.0.0.dist-info/WHEEL
spcalc-2.0.0.dist-info/entry_points.txt
spcalc-2.0.0.dist-info/top_level.txt
spcalc-2.0.0.dist-info/RECORD
