Metadata-Version: 2.1
Name: spcalc
Version: 2.0.0
Summary: Stratergy Pattern Calculator
Home-page: https://github.com/yrangana/Strategy_Pattern_Calculator
Author: Yasiru Rangana
Author-email: yrangana@gmail.com
Project-URL: Bug Tracker, https://github.com/yrangana/Strategy_Pattern_Calculator/issues
Project-URL: repository, https://github.com/yrangana/Strategy_Pattern_Calculator
Classifier: Programming Language :: Python :: 3
Classifier: License :: OSI Approved :: MIT License
Classifier: Operating System :: OS Independent
License-File: LICENSE
Requires-Dist: pylint ==3.0.3
Requires-Dist: pytest ==7.4.4
Requires-Dist: black ==23.12.1
Requires-Dist: ipython ==8.18.1
Requires-Dist: click ==8.1.7
